{
  "$schema": "https://schema.management.azure.com/schemas/2019-04-01/deploymentTemplate.json#",
  "languageVersion": "2.0",
  "contentVersion": "1.0.0.0",
  "metadata": {
    "_generator": {
      "name": "bicep",
      "version": "0.35.1.17967",
      "templateHash": "9181099812301919800"
    }
  },
  "parameters": {
    "location": {
      "type": "string",
      "defaultValue": "[resourceGroup().location]",
      "metadata": {
        "description": "The location for all resources"
      }
    },
    "environmentName": {
      "type": "string",
      "defaultValue": "dev",
      "minLength": 3,
      "maxLength": 10,
      "metadata": {
        "description": "Environment name (e.g., dev, staging, prod)"
      }
    },
    "uniqueSuffix": {
      "type": "string",
      "defaultValue": "[uniqueString(resourceGroup().id)]",
      "metadata": {
        "description": "Unique suffix for resource names to ensure global uniqueness"
      }
    },
    "frontendImage": {
      "type": "string",
      "defaultValue": "ghcr.io/michalmar/petpal-ui:latest",
      "metadata": {
        "description": "Frontend container image"
      }
    },
    "enableGitHubManagedIdentity": {
      "type": "bool",
      "defaultValue": true,
      "metadata": {
        "description": "Toggle creation of the user-assigned managed identity for GitHub Actions federation"
      }
    },
    "githubRepository": {
      "type": "string",
      "defaultValue": "michalmar/MicroHack-GitHub",
      "minLength": 3,
      "metadata": {
        "description": "Repository in owner/name format used when constructing GitHub federated credentials"
      }
    },
    "githubFederatedSubjects": {
      "type": "array",
      "defaultValue": [
        "[format('repo:{0}:ref:refs/heads/main', parameters('githubRepository'))]"
      ],
      "metadata": {
        "description": "Subjects for GitHub federated identity credentials (for example repo:owner/name:ref:refs/heads/main)"
      }
    }
  },
  "variables": {
    "resourcePrefix": "[format('petpal-{0}', parameters('environmentName'))]",
    "cosmosAccountName": "[format('{0}-cosmos-{1}', variables('resourcePrefix'), parameters('uniqueSuffix'))]",
    "containerAppEnvName": "[format('{0}-env-{1}', variables('resourcePrefix'), parameters('uniqueSuffix'))]",
    "logAnalyticsName": "[format('{0}-logs-{1}', variables('resourcePrefix'), parameters('uniqueSuffix'))]",
    "acrName": "[replace(format('{0}acr{1}', variables('resourcePrefix'), parameters('uniqueSuffix')), '-', '')]",
    "githubIdentityName": "[format('{0}-gha-mi-{1}', variables('resourcePrefix'), parameters('uniqueSuffix'))]"
  },
  "resources": {
    "containerRegistryExisting": {
      "condition": "[parameters('enableGitHubManagedIdentity')]",
      "existing": true,
      "type": "Microsoft.ContainerRegistry/registries",
      "apiVersion": "2023-07-01",
      "name": "[variables('acrName')]"
    },
    "githubManagedIdentity": {
      "condition": "[parameters('enableGitHubManagedIdentity')]",
      "type": "Microsoft.ManagedIdentity/userAssignedIdentities",
      "apiVersion": "2023-07-31",
      "name": "[variables('githubIdentityName')]",
      "location": "[parameters('location')]"
    },
    "githubFederatedIdentityCredentials": {
      "copy": {
        "name": "githubFederatedIdentityCredentials",
        "count": "[length(parameters('githubFederatedSubjects'))]"
      },
      "condition": "[parameters('enableGitHubManagedIdentity')]",
      "type": "Microsoft.ManagedIdentity/userAssignedIdentities/federatedIdentityCredentials",
      "apiVersion": "2023-07-31",
      "name": "[format('{0}/{1}', variables('githubIdentityName'), guid(resourceId('Microsoft.ManagedIdentity/userAssignedIdentities', variables('githubIdentityName')), parameters('githubFederatedSubjects')[copyIndex()]))]",
      "properties": {
        "issuer": "https://token.actions.githubusercontent.com",
        "subject": "[parameters('githubFederatedSubjects')[copyIndex()]]",
        "audiences": [
          "api://AzureADTokenExchange"
        ]
      },
      "dependsOn": [
        "githubManagedIdentity"
      ]
    },
    "githubIdentityContributorRole": {
      "condition": "[parameters('enableGitHubManagedIdentity')]",
      "type": "Microsoft.Authorization/roleAssignments",
      "apiVersion": "2022-04-01",
      "name": "[guid(subscription().subscriptionId, resourceId('Microsoft.ManagedIdentity/userAssignedIdentities', variables('githubIdentityName')), 'contributor')]",
      "properties": {
        "roleDefinitionId": "[subscriptionResourceId('Microsoft.Authorization/roleDefinitions', 'b24988ac-6180-42a0-ab88-20f7382dd24c')]",
        "principalId": "[reference('githubManagedIdentity').principalId]",
        "principalType": "ServicePrincipal"
      },
      "dependsOn": [
        "githubManagedIdentity"
      ]
    },
    "githubIdentityAcrPushRole": {
      "condition": "[parameters('enableGitHubManagedIdentity')]",
      "type": "Microsoft.Authorization/roleAssignments",
      "apiVersion": "2022-04-01",
      "scope": "[format('Microsoft.ContainerRegistry/registries/{0}', variables('acrName'))]",
      "name": "[guid(subscription().subscriptionId, resourceId('Microsoft.ManagedIdentity/userAssignedIdentities', variables('githubIdentityName')), 'acr-push')]",
      "properties": {
        "roleDefinitionId": "[subscriptionResourceId('Microsoft.Authorization/roleDefinitions', '8311e382-0749-4cb8-b61a-304f252e45ec')]",
        "principalId": "[reference('githubManagedIdentity').principalId]",
        "principalType": "ServicePrincipal"
      },
      "dependsOn": [
        "githubManagedIdentity"
      ]
    },
    "containerRegistry": {
      "type": "Microsoft.Resources/deployments",
      "apiVersion": "2022-09-01",
      "name": "acr-deployment",
      "properties": {
        "expressionEvaluationOptions": {
          "scope": "inner"
        },
        "mode": "Incremental",
        "parameters": {
          "name": {
            "value": "[variables('acrName')]"
          },
          "location": {
            "value": "[parameters('location')]"
          },
          "sku": {
            "value": "Basic"
          },
          "adminUserEnabled": {
            "value": false
          }
        },
        "template": {
          "$schema": "https://schema.management.azure.com/schemas/2019-04-01/deploymentTemplate.json#",
          "contentVersion": "1.0.0.0",
          "metadata": {
            "_generator": {
              "name": "bicep",
              "version": "0.35.1.17967",
              "templateHash": "5184970267309855671"
            }
          },
          "parameters": {
            "name": {
              "type": "string",
              "metadata": {
                "description": "Name of the Azure Container Registry"
              }
            },
            "location": {
              "type": "string",
              "defaultValue": "[resourceGroup().location]",
              "metadata": {
                "description": "Location for the Container Registry"
              }
            },
            "sku": {
              "type": "string",
              "defaultValue": "Basic",
              "allowedValues": [
                "Basic",
                "Standard",
                "Premium"
              ],
              "metadata": {
                "description": "Container Registry SKU"
              }
            },
            "adminUserEnabled": {
              "type": "bool",
              "defaultValue": true,
              "metadata": {
                "description": "Enable admin user for simplified authentication (dev/test only)"
              }
            }
          },
          "resources": [
            {
              "type": "Microsoft.ContainerRegistry/registries",
              "apiVersion": "2023-07-01",
              "name": "[parameters('name')]",
              "location": "[parameters('location')]",
              "sku": {
                "name": "[parameters('sku')]"
              },
              "properties": {
                "adminUserEnabled": "[parameters('adminUserEnabled')]",
                "publicNetworkAccess": "Enabled",
                "networkRuleBypassOptions": "AzureServices",
                "policies": {
                  "quarantinePolicy": {
                    "status": "disabled"
                  },
                  "trustPolicy": {
                    "type": "Notary",
                    "status": "disabled"
                  },
                  "retentionPolicy": {
                    "days": 7,
                    "status": "disabled"
                  }
                }
              }
            }
          ],
          "outputs": {
            "loginServer": {
              "type": "string",
              "value": "[reference(resourceId('Microsoft.ContainerRegistry/registries', parameters('name')), '2023-07-01').loginServer]"
            },
            "name": {
              "type": "string",
              "value": "[parameters('name')]"
            },
            "id": {
              "type": "string",
              "value": "[resourceId('Microsoft.ContainerRegistry/registries', parameters('name'))]"
            }
          }
        }
      }
    },
    "cosmosDb": {
      "type": "Microsoft.Resources/deployments",
      "apiVersion": "2022-09-01",
      "name": "cosmosdb-deployment",
      "properties": {
        "expressionEvaluationOptions": {
          "scope": "inner"
        },
        "mode": "Incremental",
        "parameters": {
          "accountName": {
            "value": "[variables('cosmosAccountName')]"
          },
          "location": {
            "value": "[parameters('location')]"
          }
        },
        "template": {
          "$schema": "https://schema.management.azure.com/schemas/2019-04-01/deploymentTemplate.json#",
          "languageVersion": "2.0",
          "contentVersion": "1.0.0.0",
          "metadata": {
            "_generator": {
              "name": "bicep",
              "version": "0.35.1.17967",
              "templateHash": "15165912586969604217"
            }
          },
          "parameters": {
            "accountName": {
              "type": "string",
              "metadata": {
                "description": "Cosmos DB account name"
              }
            },
            "location": {
              "type": "string",
              "defaultValue": "[resourceGroup().location]",
              "metadata": {
                "description": "Location for the Cosmos DB account"
              }
            },
            "defaultConsistencyLevel": {
              "type": "string",
              "defaultValue": "Session",
              "allowedValues": [
                "Eventual",
                "ConsistentPrefix",
                "Session",
                "BoundedStaleness",
                "Strong"
              ],
              "metadata": {
                "description": "The default consistency level of the Cosmos DB account"
              }
            }
          },
          "resources": {
            "cosmosAccount": {
              "type": "Microsoft.DocumentDB/databaseAccounts",
              "apiVersion": "2025-04-15",
              "name": "[parameters('accountName')]",
              "location": "[parameters('location')]",
              "kind": "GlobalDocumentDB",
              "properties": {
                "databaseAccountOfferType": "Standard",
                "consistencyPolicy": {
                  "defaultConsistencyLevel": "[parameters('defaultConsistencyLevel')]"
                },
                "locations": [
                  {
                    "locationName": "[parameters('location')]",
                    "failoverPriority": 0,
                    "isZoneRedundant": false
                  }
                ],
                "capabilities": [
                  {
                    "name": "EnableServerless"
                  }
                ],
                "enableFreeTier": false,
                "enableAutomaticFailover": false,
                "enableMultipleWriteLocations": false,
                "publicNetworkAccess": "Enabled",
                "disableKeyBasedMetadataWriteAccess": false
              }
            }
          },
          "outputs": {
            "endpoint": {
              "type": "string",
              "value": "[reference('cosmosAccount').documentEndpoint]"
            },
            "primaryKey": {
              "type": "string",
              "value": "[listKeys('cosmosAccount', '2025-04-15').primaryMasterKey]"
            },
            "accountName": {
              "type": "string",
              "value": "[parameters('accountName')]"
            },
            "accountId": {
              "type": "string",
              "value": "[resourceId('Microsoft.DocumentDB/databaseAccounts', parameters('accountName'))]"
            }
          }
        }
      }
    },
    "containerAppEnvironment": {
      "type": "Microsoft.Resources/deployments",
      "apiVersion": "2022-09-01",
      "name": "container-app-env-deployment",
      "properties": {
        "expressionEvaluationOptions": {
          "scope": "inner"
        },
        "mode": "Incremental",
        "parameters": {
          "environmentName": {
            "value": "[variables('containerAppEnvName')]"
          },
          "logAnalyticsName": {
            "value": "[variables('logAnalyticsName')]"
          },
          "location": {
            "value": "[parameters('location')]"
          }
        },
        "template": {
          "$schema": "https://schema.management.azure.com/schemas/2019-04-01/deploymentTemplate.json#",
          "contentVersion": "1.0.0.0",
          "metadata": {
            "_generator": {
              "name": "bicep",
              "version": "0.35.1.17967",
              "templateHash": "12468412439942943171"
            }
          },
          "parameters": {
            "environmentName": {
              "type": "string",
              "metadata": {
                "description": "Name of the Container Apps Environment"
              }
            },
            "logAnalyticsName": {
              "type": "string",
              "metadata": {
                "description": "Name of the Log Analytics workspace"
              }
            },
            "location": {
              "type": "string",
              "defaultValue": "[resourceGroup().location]",
              "metadata": {
                "description": "Location for resources"
              }
            }
          },
          "resources": [
            {
              "type": "Microsoft.OperationalInsights/workspaces",
              "apiVersion": "2021-06-01",
              "name": "[parameters('logAnalyticsName')]",
              "location": "[parameters('location')]",
              "properties": {
                "sku": {
                  "name": "PerGB2018"
                },
                "retentionInDays": 30
              }
            },
            {
              "type": "Microsoft.App/managedEnvironments",
              "apiVersion": "2024-03-01",
              "name": "[parameters('environmentName')]",
              "location": "[parameters('location')]",
              "properties": {
                "appLogsConfiguration": {
                  "destination": "log-analytics",
                  "logAnalyticsConfiguration": {
                    "customerId": "[reference(resourceId('Microsoft.OperationalInsights/workspaces', parameters('logAnalyticsName')), '2021-06-01').customerId]",
                    "sharedKey": "[listKeys(resourceId('Microsoft.OperationalInsights/workspaces', parameters('logAnalyticsName')), '2021-06-01').primarySharedKey]"
                  }
                }
              },
              "dependsOn": [
                "[resourceId('Microsoft.OperationalInsights/workspaces', parameters('logAnalyticsName'))]"
              ]
            }
          ],
          "outputs": {
            "environmentId": {
              "type": "string",
              "value": "[resourceId('Microsoft.App/managedEnvironments', parameters('environmentName'))]"
            },
            "environmentName": {
              "type": "string",
              "value": "[parameters('environmentName')]"
            },
            "defaultDomain": {
              "type": "string",
              "value": "[reference(resourceId('Microsoft.App/managedEnvironments', parameters('environmentName')), '2024-03-01').defaultDomain]"
            }
          }
        }
      }
    },
    "petService": {
      "type": "Microsoft.Resources/deployments",
      "apiVersion": "2022-09-01",
      "name": "pet-service-deployment",
      "properties": {
        "expressionEvaluationOptions": {
          "scope": "inner"
        },
        "mode": "Incremental",
        "parameters": {
          "name": {
            "value": "[format('{0}-pet-service', variables('resourcePrefix'))]"
          },
          "location": {
            "value": "[parameters('location')]"
          },
          "containerAppEnvironmentId": {
            "value": "[reference('containerAppEnvironment').outputs.environmentId.value]"
          },
          "cosmosEndpoint": {
            "value": "[reference('cosmosDb').outputs.endpoint.value]"
          },
          "cosmosKey": {
            "value": "[reference('cosmosDb').outputs.primaryKey.value]"
          }
        },
        "template": {
          "$schema": "https://schema.management.azure.com/schemas/2019-04-01/deploymentTemplate.json#",
          "contentVersion": "1.0.0.0",
          "metadata": {
            "_generator": {
              "name": "bicep",
              "version": "0.35.1.17967",
              "templateHash": "4971731420811771879"
            }
          },
          "parameters": {
            "name": {
              "type": "string",
              "metadata": {
                "description": "Name of the Container App"
              }
            },
            "location": {
              "type": "string",
              "defaultValue": "[resourceGroup().location]",
              "metadata": {
                "description": "Location for the Container App"
              }
            },
            "containerAppEnvironmentId": {
              "type": "string",
              "metadata": {
                "description": "Container Apps Environment ID"
              }
            },
            "cosmosEndpoint": {
              "type": "string",
              "metadata": {
                "description": "Cosmos DB endpoint"
              }
            },
            "cosmosKey": {
              "type": "securestring",
              "metadata": {
                "description": "Cosmos DB key"
              }
            },
            "cosmosDatabaseName": {
              "type": "string",
              "defaultValue": "petservice",
              "metadata": {
                "description": "Cosmos DB database name"
              }
            },
            "cosmosContainerName": {
              "type": "string",
              "defaultValue": "pets",
              "metadata": {
                "description": "Cosmos DB container name"
              }
            }
          },
          "resources": [
            {
              "type": "Microsoft.App/containerApps",
              "apiVersion": "2024-03-01",
              "name": "[parameters('name')]",
              "location": "[parameters('location')]",
              "properties": {
                "environmentId": "[parameters('containerAppEnvironmentId')]",
                "configuration": {
                  "ingress": {
                    "external": true,
                    "targetPort": 80,
                    "transport": "auto",
                    "allowInsecure": false
                  },
                  "secrets": [
                    {
                      "name": "cosmos-key",
                      "value": "[parameters('cosmosKey')]"
                    }
                  ]
                },
                "template": {
                  "containers": [
                    {
                      "name": "simple-hello",
                      "image": "mcr.microsoft.com/azuredocs/containerapps-helloworld:latest",
                      "resources": {
                        "cpu": "[json('0.5')]",
                        "memory": "1Gi"
                      },
                      "env": [
                        {
                          "name": "COSMOS_ENDPOINT",
                          "value": "[parameters('cosmosEndpoint')]"
                        },
                        {
                          "name": "COSMOS_KEY",
                          "secretRef": "cosmos-key"
                        },
                        {
                          "name": "COSMOS_DATABASE_NAME",
                          "value": "[parameters('cosmosDatabaseName')]"
                        },
                        {
                          "name": "COSMOS_CONTAINER_NAME",
                          "value": "[parameters('cosmosContainerName')]"
                        }
                      ]
                    }
                  ],
                  "scale": {
                    "minReplicas": 1,
                    "maxReplicas": 10,
                    "rules": [
                      {
                        "name": "http-rule",
                        "http": {
                          "metadata": {
                            "concurrentRequests": "10"
                          }
                        }
                      }
                    ]
                  }
                }
              }
            }
          ],
          "outputs": {
            "fqdn": {
              "type": "string",
              "value": "[format('https://{0}', reference(resourceId('Microsoft.App/containerApps', parameters('name')), '2024-03-01').configuration.ingress.fqdn)]"
            },
            "name": {
              "type": "string",
              "value": "[parameters('name')]"
            },
            "id": {
              "type": "string",
              "value": "[resourceId('Microsoft.App/containerApps', parameters('name'))]"
            }
          }
        }
      },
      "dependsOn": [
        "containerAppEnvironment",
        "cosmosDb"
      ]
    },
    "activityService": {
      "type": "Microsoft.Resources/deployments",
      "apiVersion": "2022-09-01",
      "name": "activity-service-deployment",
      "properties": {
        "expressionEvaluationOptions": {
          "scope": "inner"
        },
        "mode": "Incremental",
        "parameters": {
          "name": {
            "value": "[format('{0}-activity-service', variables('resourcePrefix'))]"
          },
          "location": {
            "value": "[parameters('location')]"
          },
          "containerAppEnvironmentId": {
            "value": "[reference('containerAppEnvironment').outputs.environmentId.value]"
          },
          "cosmosEndpoint": {
            "value": "[reference('cosmosDb').outputs.endpoint.value]"
          },
          "cosmosKey": {
            "value": "[reference('cosmosDb').outputs.primaryKey.value]"
          }
        },
        "template": {
          "$schema": "https://schema.management.azure.com/schemas/2019-04-01/deploymentTemplate.json#",
          "contentVersion": "1.0.0.0",
          "metadata": {
            "_generator": {
              "name": "bicep",
              "version": "0.35.1.17967",
              "templateHash": "5509449213987833358"
            }
          },
          "parameters": {
            "name": {
              "type": "string",
              "metadata": {
                "description": "Name of the Container App"
              }
            },
            "location": {
              "type": "string",
              "defaultValue": "[resourceGroup().location]",
              "metadata": {
                "description": "Location for the Container App"
              }
            },
            "containerAppEnvironmentId": {
              "type": "string",
              "metadata": {
                "description": "Container Apps Environment ID"
              }
            },
            "cosmosEndpoint": {
              "type": "string",
              "metadata": {
                "description": "Cosmos DB endpoint"
              }
            },
            "cosmosKey": {
              "type": "securestring",
              "metadata": {
                "description": "Cosmos DB key"
              }
            },
            "cosmosDatabaseName": {
              "type": "string",
              "defaultValue": "activityservice",
              "metadata": {
                "description": "Cosmos DB database name"
              }
            },
            "cosmosContainerName": {
              "type": "string",
              "defaultValue": "activities",
              "metadata": {
                "description": "Cosmos DB container name"
              }
            }
          },
          "resources": [
            {
              "type": "Microsoft.App/containerApps",
              "apiVersion": "2024-03-01",
              "name": "[parameters('name')]",
              "location": "[parameters('location')]",
              "properties": {
                "environmentId": "[parameters('containerAppEnvironmentId')]",
                "configuration": {
                  "ingress": {
                    "external": true,
                    "targetPort": 80,
                    "transport": "auto",
                    "allowInsecure": false
                  },
                  "secrets": [
                    {
                      "name": "cosmos-key",
                      "value": "[parameters('cosmosKey')]"
                    }
                  ]
                },
                "template": {
                  "containers": [
                    {
                      "name": "simple-hello",
                      "image": "mcr.microsoft.com/azuredocs/containerapps-helloworld:latest",
                      "resources": {
                        "cpu": "[json('0.5')]",
                        "memory": "1Gi"
                      },
                      "env": [
                        {
                          "name": "COSMOS_ENDPOINT",
                          "value": "[parameters('cosmosEndpoint')]"
                        },
                        {
                          "name": "COSMOS_KEY",
                          "secretRef": "cosmos-key"
                        },
                        {
                          "name": "COSMOS_DATABASE_NAME",
                          "value": "[parameters('cosmosDatabaseName')]"
                        },
                        {
                          "name": "COSMOS_CONTAINER_NAME",
                          "value": "[parameters('cosmosContainerName')]"
                        }
                      ]
                    }
                  ],
                  "scale": {
                    "minReplicas": 1,
                    "maxReplicas": 10,
                    "rules": [
                      {
                        "name": "http-rule",
                        "http": {
                          "metadata": {
                            "concurrentRequests": "10"
                          }
                        }
                      }
                    ]
                  }
                }
              }
            }
          ],
          "outputs": {
            "fqdn": {
              "type": "string",
              "value": "[format('https://{0}', reference(resourceId('Microsoft.App/containerApps', parameters('name')), '2024-03-01').configuration.ingress.fqdn)]"
            },
            "name": {
              "type": "string",
              "value": "[parameters('name')]"
            },
            "id": {
              "type": "string",
              "value": "[resourceId('Microsoft.App/containerApps', parameters('name'))]"
            }
          }
        }
      },
      "dependsOn": [
        "containerAppEnvironment",
        "cosmosDb"
      ]
    },
    "accessoryService": {
      "type": "Microsoft.Resources/deployments",
      "apiVersion": "2022-09-01",
      "name": "accessory-service-deployment",
      "properties": {
        "expressionEvaluationOptions": {
          "scope": "inner"
        },
        "mode": "Incremental",
        "parameters": {
          "name": {
            "value": "[format('{0}-accessory-service', variables('resourcePrefix'))]"
          },
          "location": {
            "value": "[parameters('location')]"
          },
          "containerAppEnvironmentId": {
            "value": "[reference('containerAppEnvironment').outputs.environmentId.value]"
          },
          "cosmosEndpoint": {
            "value": "[reference('cosmosDb').outputs.endpoint.value]"
          },
          "cosmosKey": {
            "value": "[reference('cosmosDb').outputs.primaryKey.value]"
          }
        },
        "template": {
          "$schema": "https://schema.management.azure.com/schemas/2019-04-01/deploymentTemplate.json#",
          "contentVersion": "1.0.0.0",
          "metadata": {
            "_generator": {
              "name": "bicep",
              "version": "0.35.1.17967",
              "templateHash": "7724864624258912458"
            }
          },
          "parameters": {
            "name": {
              "type": "string",
              "metadata": {
                "description": "Name of the Container App"
              }
            },
            "location": {
              "type": "string",
              "defaultValue": "[resourceGroup().location]",
              "metadata": {
                "description": "Location for the Container App"
              }
            },
            "containerAppEnvironmentId": {
              "type": "string",
              "metadata": {
                "description": "Container Apps Environment ID"
              }
            },
            "cosmosEndpoint": {
              "type": "string",
              "metadata": {
                "description": "Cosmos DB endpoint"
              }
            },
            "cosmosKey": {
              "type": "securestring",
              "metadata": {
                "description": "Cosmos DB key"
              }
            },
            "cosmosDatabaseName": {
              "type": "string",
              "defaultValue": "accessoryservice",
              "metadata": {
                "description": "Cosmos DB database name"
              }
            },
            "cosmosContainerName": {
              "type": "string",
              "defaultValue": "accessories",
              "metadata": {
                "description": "Cosmos DB container name"
              }
            }
          },
          "resources": [
            {
              "type": "Microsoft.App/containerApps",
              "apiVersion": "2024-03-01",
              "name": "[parameters('name')]",
              "location": "[parameters('location')]",
              "properties": {
                "environmentId": "[parameters('containerAppEnvironmentId')]",
                "configuration": {
                  "ingress": {
                    "external": true,
                    "targetPort": 80,
                    "transport": "auto",
                    "allowInsecure": false
                  },
                  "secrets": [
                    {
                      "name": "cosmos-key",
                      "value": "[parameters('cosmosKey')]"
                    }
                  ]
                },
                "template": {
                  "containers": [
                    {
                      "name": "simple-hello",
                      "image": "mcr.microsoft.com/azuredocs/containerapps-helloworld:latest",
                      "resources": {
                        "cpu": "[json('0.5')]",
                        "memory": "1Gi"
                      },
                      "env": [
                        {
                          "name": "COSMOS_ENDPOINT",
                          "value": "[parameters('cosmosEndpoint')]"
                        },
                        {
                          "name": "COSMOS_KEY",
                          "secretRef": "cosmos-key"
                        },
                        {
                          "name": "COSMOS_DATABASE_NAME",
                          "value": "[parameters('cosmosDatabaseName')]"
                        },
                        {
                          "name": "COSMOS_CONTAINER_NAME",
                          "value": "[parameters('cosmosContainerName')]"
                        }
                      ]
                    }
                  ],
                  "scale": {
                    "minReplicas": 1,
                    "maxReplicas": 10,
                    "rules": [
                      {
                        "name": "http-rule",
                        "http": {
                          "metadata": {
                            "concurrentRequests": "10"
                          }
                        }
                      }
                    ]
                  }
                }
              }
            }
          ],
          "outputs": {
            "fqdn": {
              "type": "string",
              "value": "[format('https://{0}', reference(resourceId('Microsoft.App/containerApps', parameters('name')), '2024-03-01').configuration.ingress.fqdn)]"
            },
            "name": {
              "type": "string",
              "value": "[parameters('name')]"
            },
            "id": {
              "type": "string",
              "value": "[resourceId('Microsoft.App/containerApps', parameters('name'))]"
            }
          }
        }
      },
      "dependsOn": [
        "containerAppEnvironment",
        "cosmosDb"
      ]
    },
    "frontend": {
      "type": "Microsoft.Resources/deployments",
      "apiVersion": "2022-09-01",
      "name": "frontend-deployment",
      "properties": {
        "expressionEvaluationOptions": {
          "scope": "inner"
        },
        "mode": "Incremental",
        "parameters": {
          "name": {
            "value": "[format('{0}-frontend', variables('resourcePrefix'))]"
          },
          "location": {
            "value": "[parameters('location')]"
          },
          "containerAppEnvironmentId": {
            "value": "[reference('containerAppEnvironment').outputs.environmentId.value]"
          },
          "frontendImage": {
            "value": "[parameters('frontendImage')]"
          },
          "petServiceUrl": {
            "value": "[reference('petService').outputs.fqdn.value]"
          },
          "activityServiceUrl": {
            "value": "[reference('activityService').outputs.fqdn.value]"
          },
          "accessoryServiceUrl": {
            "value": "[reference('accessoryService').outputs.fqdn.value]"
          }
        },
        "template": {
          "$schema": "https://schema.management.azure.com/schemas/2019-04-01/deploymentTemplate.json#",
          "contentVersion": "1.0.0.0",
          "metadata": {
            "_generator": {
              "name": "bicep",
              "version": "0.35.1.17967",
              "templateHash": "13881357313528383482"
            }
          },
          "parameters": {
            "name": {
              "type": "string",
              "metadata": {
                "description": "Name of the Container App"
              }
            },
            "location": {
              "type": "string",
              "defaultValue": "[resourceGroup().location]",
              "metadata": {
                "description": "Location for the Container App"
              }
            },
            "containerAppEnvironmentId": {
              "type": "string",
              "metadata": {
                "description": "Container Apps Environment ID"
              }
            },
            "frontendImage": {
              "type": "string",
              "metadata": {
                "description": "Frontend container image"
              }
            },
            "petServiceUrl": {
              "type": "string",
              "metadata": {
                "description": "Pet Service URL"
              }
            },
            "activityServiceUrl": {
              "type": "string",
              "metadata": {
                "description": "Activity Service URL"
              }
            },
            "accessoryServiceUrl": {
              "type": "string",
              "metadata": {
                "description": "Accessory Service URL"
              }
            }
          },
          "resources": [
            {
              "type": "Microsoft.App/containerApps",
              "apiVersion": "2024-03-01",
              "name": "[parameters('name')]",
              "location": "[parameters('location')]",
              "properties": {
                "environmentId": "[parameters('containerAppEnvironmentId')]",
                "configuration": {
                  "ingress": {
                    "external": true,
                    "targetPort": 80,
                    "transport": "auto",
                    "allowInsecure": false
                  }
                },
                "template": {
                  "containers": [
                    {
                      "name": "frontend",
                      "image": "[parameters('frontendImage')]",
                      "resources": {
                        "cpu": "[json('0.5')]",
                        "memory": "1Gi"
                      },
                      "env": [
                        {
                          "name": "VITE_API_PETS_URL",
                          "value": "[parameters('petServiceUrl')]"
                        },
                        {
                          "name": "VITE_API_ACTIVITIES_URL",
                          "value": "[parameters('activityServiceUrl')]"
                        },
                        {
                          "name": "VITE_API_ACCESSORIES_URL",
                          "value": "[parameters('accessoryServiceUrl')]"
                        }
                      ]
                    }
                  ],
                  "scale": {
                    "minReplicas": 1,
                    "maxReplicas": 5,
                    "rules": [
                      {
                        "name": "http-rule",
                        "http": {
                          "metadata": {
                            "concurrentRequests": "50"
                          }
                        }
                      }
                    ]
                  }
                }
              }
            }
          ],
          "outputs": {
            "fqdn": {
              "type": "string",
              "value": "[format('https://{0}', reference(resourceId('Microsoft.App/containerApps', parameters('name')), '2024-03-01').configuration.ingress.fqdn)]"
            },
            "name": {
              "type": "string",
              "value": "[parameters('name')]"
            },
            "id": {
              "type": "string",
              "value": "[resourceId('Microsoft.App/containerApps', parameters('name'))]"
            }
          }
        }
      },
      "dependsOn": [
        "accessoryService",
        "activityService",
        "containerAppEnvironment",
        "petService"
      ]
    }
  },
  "outputs": {
    "cosmosEndpoint": {
      "type": "string",
      "value": "[reference('cosmosDb').outputs.endpoint.value]"
    },
    "acrLoginServer": {
      "type": "string",
      "value": "[reference('containerRegistry').outputs.loginServer.value]"
    },
    "acrName": {
      "type": "string",
      "value": "[reference('containerRegistry').outputs.name.value]"
    },
    "acrResourceId": {
      "type": "string",
      "value": "[reference('containerRegistry').outputs.id.value]"
    },
    "petServiceUrl": {
      "type": "string",
      "value": "[reference('petService').outputs.fqdn.value]"
    },
    "activityServiceUrl": {
      "type": "string",
      "value": "[reference('activityService').outputs.fqdn.value]"
    },
    "accessoryServiceUrl": {
      "type": "string",
      "value": "[reference('accessoryService').outputs.fqdn.value]"
    },
    "frontendUrl": {
      "type": "string",
      "value": "[reference('frontend').outputs.fqdn.value]"
    },
    "githubManagedIdentityClientId": {
      "type": "string",
      "value": "[if(parameters('enableGitHubManagedIdentity'), reference('githubManagedIdentity').clientId, '')]"
    },
    "githubManagedIdentityPrincipalId": {
      "type": "string",
      "value": "[if(parameters('enableGitHubManagedIdentity'), reference('githubManagedIdentity').principalId, '')]"
    },
    "githubManagedIdentityResourceId": {
      "type": "string",
      "value": "[if(parameters('enableGitHubManagedIdentity'), resourceId('Microsoft.ManagedIdentity/userAssignedIdentities', variables('githubIdentityName')), '')]"
    }
  }
}